pdformfill/__init__.py
pdformfill/fdf.py
pdformfill-0.0.4.dist-info/LICENSE
pdformfill-0.0.4.dist-info/METADATA
pdformfill-0.0.4.dist-info/WHEEL
pdformfill-0.0.4.dist-info/top_level.txt
pdformfill-0.0.4.dist-info/RECORD
