Metadata-Version: 2.1
Name: pdformfill
Version: 0.0.4
Summary: library for filling pdf forms
Home-page: http://github.com/frainfreeze/pdformfill
Author: Tomislav Kucar
Author-email: kucar.tomislav@gmail.com
License: BSD-3-Clause
Platform: any
